custom_functions.cp310-win_amd64.pyd
custom_functions_swipe-0.1.dist-info/METADATA
custom_functions_swipe-0.1.dist-info/WHEEL
custom_functions_swipe-0.1.dist-info/top_level.txt
custom_functions_swipe-0.1.dist-info/RECORD
